denverapi/__init__.py
denverapi/bdtp.py
denverapi/bdtp_file_server.py
denverapi/beautiful_cli.py
denverapi/bitmap.py
denverapi/cipher.py
denverapi/colored_text.py
denverapi/data_representation.py
denverapi/encryption.py
denverapi/function_logger.py
denverapi/graphics2d.py
denverapi/graphics3d.py
denverapi/input_utils.py
denverapi/recursive_imports.py
denverapi/setup_utils.py
denverapi/sound.py
denverapi/thread_control.py
denverapi/unicode_utils.py
denverapi/_colorama/__init__.py
denverapi/_colorama/ansi.py
denverapi/_colorama/ansitowin32.py
denverapi/_colorama/initialise.py
denverapi/_colorama/win32.py
denverapi/_colorama/winterm.py
denverapi/autopyb/__init__.py
denverapi/autopyb/commands/__init__.py
denverapi/autopyb/commands/distribution.py
denverapi/autopyb/commands/pip.py
denverapi/autopyb/commands/terminal.py
denverapi/clineutils/__init__.py
denverapi/clineutils/rmr.py
denverapi/clineutils/rmrdir.py
denverapi/tools/__init__.py
denverapi/tools/__main__.py
denverapi/tools/bdtpserver.py
denverapi/tools/cryptify.py
denver_api-3.0.0.dist-info/LICENSE
denver_api-3.0.0.dist-info/METADATA
denver_api-3.0.0.dist-info/WHEEL
denver_api-3.0.0.dist-info/entry_points.txt
denver_api-3.0.0.dist-info/top_level.txt
denver_api-3.0.0.dist-info/RECORD
