Metadata-Version: 2.1
Name: denver-api
Version: 3.0.0
Summary: Denver API for python full-stack development
Home-page: https://github.com/xcodz-dot/denver-api
Author: xcodz
License: UNKNOWN
Platform: UNKNOWN
Classifier: Programming Language :: Python :: 3.6
Classifier: Operating System :: OS Independent
Requires-Python: >=3.6
Requires-Dist: setuptools (>50)
Requires-Dist: requests
Requires-Dist: playsound
Requires-Dist: packaging
Requires-Dist: pip (>=21)
Requires-Dist: ansiwrap
Provides-Extra: all
Requires-Dist: pygame ; extra == 'all'
Requires-Dist: pycryptodomex ; extra == 'all'
Provides-Extra: encryption
Requires-Dist: pycryptodomex ; extra == 'encryption'
Provides-Extra: gui-tools
Requires-Dist: pygame ; extra == 'gui-tools'
